cherwell_pydantic_api/__init__.py
cherwell_pydantic_api/__main__.py
cherwell_pydantic_api/_generated/api/__init__.py
cherwell_pydantic_api/_generated/api/endpoints/Approval.py
cherwell_pydantic_api/_generated/api/endpoints/BusinessObject.py
cherwell_pydantic_api/_generated/api/endpoints/Core.py
cherwell_pydantic_api/_generated/api/endpoints/Forms.py
cherwell_pydantic_api/_generated/api/endpoints/Lifecycle.py
cherwell_pydantic_api/_generated/api/endpoints/OneStepActions.py
cherwell_pydantic_api/_generated/api/endpoints/Queues.py
cherwell_pydantic_api/_generated/api/endpoints/Searches.py
cherwell_pydantic_api/_generated/api/endpoints/Security.py
cherwell_pydantic_api/_generated/api/endpoints/Service.py
cherwell_pydantic_api/_generated/api/endpoints/Teams.py
cherwell_pydantic_api/_generated/api/endpoints/Users.py
cherwell_pydantic_api/_generated/api/endpoints/__init__.py
cherwell_pydantic_api/_generated/api/models/Trebuchet/WebApi/DataContracts/Approval.py
cherwell_pydantic_api/_generated/api/models/Trebuchet/WebApi/DataContracts/BusinessObject.py
cherwell_pydantic_api/_generated/api/models/Trebuchet/WebApi/DataContracts/Core.py
cherwell_pydantic_api/_generated/api/models/Trebuchet/WebApi/DataContracts/Forms.py
cherwell_pydantic_api/_generated/api/models/Trebuchet/WebApi/DataContracts/Lifecycle.py
cherwell_pydantic_api/_generated/api/models/Trebuchet/WebApi/DataContracts/OneStepActions.py
cherwell_pydantic_api/_generated/api/models/Trebuchet/WebApi/DataContracts/Queues.py
cherwell_pydantic_api/_generated/api/models/Trebuchet/WebApi/DataContracts/Searches.py
cherwell_pydantic_api/_generated/api/models/Trebuchet/WebApi/DataContracts/Security.py
cherwell_pydantic_api/_generated/api/models/Trebuchet/WebApi/DataContracts/Teams.py
cherwell_pydantic_api/_generated/api/models/Trebuchet/WebApi/DataContracts/Users.py
cherwell_pydantic_api/_generated/api/models/Trebuchet/WebApi/DataContracts/__init__.py
cherwell_pydantic_api/_generated/api/models/Trebuchet/WebApi/__init__.py
cherwell_pydantic_api-0.0.5.dist-info/LICENSE.md
cherwell_pydantic_api-0.0.5.dist-info/METADATA
cherwell_pydantic_api-0.0.5.dist-info/WHEEL
cherwell_pydantic_api-0.0.5.dist-info/entry_points.txt
cherwell_pydantic_api-0.0.5.dist-info/RECORD
